LICENSE
README.md
setup.py
echorev/__init__.py
echorev/get.png
echorev/getB.py
echorev/github.png
echorev/icon.png
echorev/quit.png
echorev/setup.py
echorev/test.py
echorev/testGPG.py
echorev/tmp.py
echorev/update.png
echorev.egg-info/PKG-INFO
echorev.egg-info/SOURCES.txt
echorev.egg-info/dependency_links.txt
echorev.egg-info/requires.txt
echorev.egg-info/top_level.txt